httpasilib/__init__.py
httpasilib/util.py
httpasilib-2.0.0.dist-info/LICENSE.txt
httpasilib-2.0.0.dist-info/METADATA
httpasilib-2.0.0.dist-info/WHEEL
httpasilib-2.0.0.dist-info/dependency_links.txt
httpasilib-2.0.0.dist-info/top_level.txt
httpasilib-2.0.0.dist-info/zip-safe
httpasilib-2.0.0.dist-info/RECORD
