Metadata-Version: 2.1
Name: httpasilib
Version: 2.0.0
Summary: Aalto Social Interface (ASI) Python interface library
Home-page: http://asibsync.sourceforge.net
Author: Eemeli Kantola
Author-email: eemeli.kantola@iki.fi
License: BSD
Keywords: ASI REST OtaSizzle
Classifier: Development Status :: 4 - Beta
Classifier: Environment :: Web Environment
Classifier: Intended Audience :: Developers
Classifier: License :: OSI Approved :: BSD License
Classifier: Programming Language :: Python :: 2.6
Classifier: Topic :: Internet
License-File: LICENSE.txt
Requires-Dist: restlib >=0.9
Requires-Dist: opensocial.py
Provides-Extra: test
Requires-Dist: minimock ; extra == 'test'
